src/__init__.py
src/main.py
src/test_main.py
src/detector/__init__.py
src/detector/audio_detector.py
src/detector/test_audio_detector.py
src/detector/processors/__init__.py
src/detector/processors/rms_processor.py
src/detector/processors/test_rms_processor.py
src/localization/__init__.py
src/localization/translations/en.json
src/localization/translations/es.json
src/notifiers/__init__.py
src/notifiers/base.py
src/notifiers/slack.py
src/notifiers/test_base.py
src/notifiers/test_slack.py
src/recorders/__init__.py
src/recorders/base.py
src/recorders/test_base.py
src/recorders/test_wave_recorder.py
src/recorders/wave_recorder.py
src/utils/__init__.py
src/utils/config.py
src/utils/logger.py
src/utils/test_config.py
src/utils/test_logger.py
loud_noise_detector-2.0.2.dist-info/METADATA
loud_noise_detector-2.0.2.dist-info/WHEEL
loud_noise_detector-2.0.2.dist-info/entry_points.txt
loud_noise_detector-2.0.2.dist-info/top_level.txt
loud_noise_detector-2.0.2.dist-info/RECORD
