Metadata-Version: 2.4
Name: loud_noise_detector
Version: 2.0.2
Summary: Audio monitoring system that detects and alerts you about important sounds in your home while you're away. Perfect for pet owners and parents who need to stay connected to their space.
Home-page: https://github.com/Endika/loud-noise-detector
Author: Endika Iglesias
Author-email: endika2@gmail.com
Project-URL: Source Code, https://github.com/Endika/loud-noise-detector
Project-URL: Bug Tracker, https://github.com/Endika/loud-noise-detector/issues
Keywords: AudioMonitoring,PetCare,BabyMonitor,SoundDetection,DigitalParenting,SmartSolution,audio,detection,recording,notification
Classifier: Development Status :: 3 - Alpha
Classifier: Intended Audience :: Developers
Classifier: License :: OSI Approved :: MIT License
Classifier: Programming Language :: Python :: 3
Classifier: Programming Language :: Python :: 3.6
Classifier: Programming Language :: Python :: 3.7
Classifier: Programming Language :: Python :: 3.8
Classifier: Programming Language :: Python :: 3.9
Requires-Python: >=3.6
Requires-Dist: pyaudio>=0.2.11
Requires-Dist: pyyaml>=5.1
Requires-Dist: requests>=2.25.0
Requires-Dist: numpy>=2.0.2
Requires-Dist: python-dotenv>=1.0.1
Dynamic: author
Dynamic: author-email
Dynamic: classifier
Dynamic: description
Dynamic: description-content-type
Dynamic: home-page
Dynamic: keywords
Dynamic: project-url
Dynamic: requires-dist
Dynamic: requires-python
Dynamic: summary
